{
	"version": "0.0.1",
	"theme": {
		"leaderboard": {
			"panelBody": " #FFFFFF",
			"scoresBody": "#73D7EE",
			"rowEntry": "#FFAFC7",
			"yourRowEntry": "#FFFFFF",
			"headerText": "#000000",
			"text": "#000000",
			"textOutline": "#FFFFFF",
			"slider": {
				"handle": "#964B00",
				"background": "#FFFFFF",
				"fill": "#000000"
			},
			"tabs": {
				"normal": "#FFFFFF",
				"pressed": "#FFFFFF",
				"highlighted": "#FFFFFF"
			}
		},
		"scrollSpeedSlider": {
			"handle": "#964B00",
			"text": "#FFFFFF",
			"background": "#FFFFFF",
			"fill": "#000000"
		},
		"notification": {
			"border": "#FFAFC7",
			"background": "#FFFFFF",
			"defaultText": "#73D7EE",
			"warningText": "#73D7EE",
			"errorText": "#73D7EE",
			"textOutline": "#301934"
		},
		"replayButton": {
			"text": "#000000",
			"normal": "#FFFFFF",
			"pressed": "#770088",
			"highlighted": "#FFAFC7"
		},
		"capsules": {
			"year": "#E50000",
			"yearShadow": "#301934",
			"composer": "#FFEE00",
			"composerShadow": "#301934",
			"genre": "#FF8D00",
			"genreShadow": "#301934",
			"description": "#004CFF",
			"descriptionShadow": "#301934",
			"tempo": "#028121"
		},
		"randomButton": {
			"background": "#004CFF",
			"backgroundOver": "#73D7EE",
			"outline": "#301934",
			"outlineOver": "#301934",
			"text": "#000000",
			"textOver": "#FFFFFF"
		},
		"backButton": {
			"background": "#FF8D00",
			"backgroundOver": "#FFEE00",
			"outline": "#301934",
			"outlineOver": "#301934",
			"text": "#FFFFFF",
			"textOver": "#000000",
			"shadow": "#301934",
			"shadowOver": "#301934"
		},
		"playButton": {
			"background": "#004CFF",
			"backgroundOver": "#73D7EE",
			"outline": "#301934",
			"outlineOver": "#301934",
			"text": "#FFFFFF",
			"textOver": "#000000",
			"shadow": "#964B00",
			"shadowOver": "#000000"
		},
		"songButton": {
			"background": "#004CFF",
			"text": "#FFFFFF",
			"textOver": "#000000",
			"outline": "#301934",
			"outlineOver": "#301934",
			"shadow": "#964B00",
			"square": "#770088"
		},
		"diffStar": {
			"gradientStart": "#FFAFC7",
			"gradientEnd": "#73D7EE"
		},
		"pointer": {
			"background": "#004CFF",
			"shadow": "#964B00",
			"outline": "#301934"
		},
		"background":{
			"waves": "#028121",
			"waves2": "#FFEE00",
			"dots": "#FF8D00",
			"dots2": "#004CFF",
			"shape": "#004CFF39",
			"diamond": "#E6E6FA",
			"background": "#E50000"
	    },
		"title": {
		    "songName": "#000000",
			"titleBar": "#964B0095",
			"title": "#000000",
			"titleShadow": "#964B00"
	    }
    }
}	